wandio/__init__.py
wandio/compressed.py
wandio/file.py
wandio/http.py
wandio/opener.py
wandio/swift.py
wandio/test-write.py
wandio/test.py
wandio/wand_http.py
pywandio-0.3.0.dist-info/LICENSE
pywandio-0.3.0.dist-info/METADATA
pywandio-0.3.0.dist-info/WHEEL
pywandio-0.3.0.dist-info/entry_points.txt
pywandio-0.3.0.dist-info/top_level.txt
pywandio-0.3.0.dist-info/RECORD
